{
  "main": [
    {
      "name": "Blog",
      "url": "",
      "hasChildren": true,
      "children": [
        {
          "name": "Latest",
          "url": "/"
        },
        {
          "name": "Categories",
          "url": "/categories"
        },
        {
          "name": "Tags",
          "url": "/tags"
        }
      ]
    },
    {
      "name": "Association",
      "url": "",
      "hasChildren": true,
      "children": [
        {
          "name": "Members",
          "url": "/authors"
        },
        {
          "name": "Executive board",
          "url": "/board"
        },
        {
          "name": "Research groups",
          "url": "/groups"
        },
        {
          "name": "Statutes",
          "url": "/privacy-policy"
        }
      ]
    },
    
    {
      "name": "About",
      "url": "/about"
    },
    {
      "name": "Contact",
      "url": "/contact"
    }
  ],
  "footer": [
    {
      "name": "About",
      "url": "/about"
    },
    {
      "name": "Contact",
      "url": "/contact"
    },
    {
      "name": "Statutes",
      "url": "/privacy-policy"
    }
  ]
}
